beekeeper_chatbot_sdk/__init__.py
beekeeper_chatbot_sdk/beekeeper_chat_bot.py
beekeeper_chatbot_sdk/beekeeper_message_listener.py
beekeeper_chatbot_sdk/decrypter.py
beekeeper_chatbot_sdk/handlers.py
beekeeper_chatbot_sdk-0.3.4.dist-info/LICENSE
beekeeper_chatbot_sdk-0.3.4.dist-info/METADATA
beekeeper_chatbot_sdk-0.3.4.dist-info/WHEEL
beekeeper_chatbot_sdk-0.3.4.dist-info/top_level.txt
beekeeper_chatbot_sdk-0.3.4.dist-info/RECORD
