Metadata-Version: 2.1
Name: beekeeper-chatbot-sdk
Version: 0.3.4
Summary: SDK for creating chat bots with the Beekeeper API
Home-page: https://github.com/HappyTetrahedron/beekeeper-sdk-python
Author: Aline Abler
Author-email: alinea@riseup.net
License: UNKNOWN
Platform: UNKNOWN
Classifier: Programming Language :: Python :: 3
Classifier: License :: OSI Approved :: MIT License
Classifier: Operating System :: OS Independent
License-File: LICENSE
Requires-Dist: beekeeper-sdk (==0.3.4)
Requires-Dist: pubnub
Requires-Dist: cryptography
